README.md
env_var
pyproject.toml
setup.py
sbcli_delay.egg-info/PKG-INFO
sbcli_delay.egg-info/SOURCES.txt
sbcli_delay.egg-info/dependency_links.txt
sbcli_delay.egg-info/entry_points.txt
sbcli_delay.egg-info/requires.txt
sbcli_delay.egg-info/top_level.txt
simplyblock_cli/cli.py
simplyblock_cli/main.py
simplyblock_core/__init__.py
simplyblock_core/cluster_ops.py
simplyblock_core/cnode_client.py
simplyblock_core/compute_node_ops.py
simplyblock_core/constants.py
simplyblock_core/distr_controller.py
simplyblock_core/kv_store.py
simplyblock_core/mgmt_node_ops.py
simplyblock_core/pci_utils.py
simplyblock_core/rpc_client.py
simplyblock_core/shell_utils.py
simplyblock_core/snode_client.py
simplyblock_core/storage_node_ops.py
simplyblock_core/utils.py
simplyblock_core/controllers/__init__.py
simplyblock_core/controllers/caching_node_controller.py
simplyblock_core/controllers/cluster_events.py
simplyblock_core/controllers/device_controller.py
simplyblock_core/controllers/device_events.py
simplyblock_core/controllers/events_controller.py
simplyblock_core/controllers/health_controller.py
simplyblock_core/controllers/lvol_controller.py
simplyblock_core/controllers/lvol_events.py
simplyblock_core/controllers/mgmt_events.py
simplyblock_core/controllers/pool_controller.py
simplyblock_core/controllers/pool_events.py
simplyblock_core/controllers/snapshot_controller.py
simplyblock_core/controllers/snapshot_events.py
simplyblock_core/controllers/storage_events.py
simplyblock_core/controllers/tasks_controller.py
simplyblock_core/controllers/tasks_events.py
simplyblock_core/models/__init__.py
simplyblock_core/models/base_model.py
simplyblock_core/models/caching_node.py
simplyblock_core/models/cluster.py
simplyblock_core/models/compute_node.py
simplyblock_core/models/deployer.py
simplyblock_core/models/events.py
simplyblock_core/models/global_settings.py
simplyblock_core/models/iface.py
simplyblock_core/models/job_schedule.py
simplyblock_core/models/lvol_model.py
simplyblock_core/models/mgmt_node.py
simplyblock_core/models/nvme_device.py
simplyblock_core/models/pool.py
simplyblock_core/models/port_stat.py
simplyblock_core/models/snapshot.py
simplyblock_core/models/stats.py
